iso639_1/__init__.py
iso639_1/language.py
iso639_1-1.0.dist-info/LICENSE
iso639_1-1.0.dist-info/METADATA
iso639_1-1.0.dist-info/WHEEL
iso639_1-1.0.dist-info/top_level.txt
iso639_1-1.0.dist-info/RECORD
