Metadata-Version: 2.1
Name: iso639-1
Version: 1.0
Summary: Enum for ISO 639-1 (languages)
Home-page: https://github.com/jonathan-shemer/iso639-1
Author: Jonathan Shemer
Author-email: UNKNOWN
License: GNUv3
Platform: UNKNOWN
